{
    "content": "<OpenSearchDescription xmlns=\"http://a9.com/-/spec/opensearch/1.1/\" xmlns:moz=\"http://www.mozilla.org/2006/browser/search/\">   <ShortName>www.saja.org</ShortName>   <InputEncoding>UTF-8</InputEncoding>   <Url type=\"text/html\" method=\"get\" template=\"http://www.saja.org/sys/search?q={searchTerms}\"/> </OpenSearchDescription>", 
    "identity": {
        "subtype": "service", 
        "is_error": false, 
        "version": "1.1", 
        "protocol": "OpenSearch", 
        "language": "", 
        "service": "OpenSearchDescription", 
        "has_dataset": false, 
        "has_metadata": false
    }, 
    "digest": "07af795e528417377b5b89a5ff2e6fab", 
    "source_url": "http://www.saja.org/opensearch.ashx"
}