{
    "content": "<?xml version=\"1.0\" encoding=\"UTF-8\"?>     <thredds:catalog xmlns:fn=\"http://www.w3.org/2005/02/xpath-functions\"                  xmlns:thredds=\"http://www.unidata.ucar.edu/namespaces/thredds/InvCatalog/v1.0\"                  xmlns:xlink=\"http://www.w3.org/1999/xlink\"                  xmlns:bes=\"http://xml.opendap.org/ns/bes/1.0#\">    <thredds:service name=\"dap\" serviceType=\"OPeNDAP\" base=\"/opendap/hyrax\"/>    <thredds:service name=\"file\" serviceType=\"HTTPServer\" base=\"/opendap/hyrax\"/>         <thredds:dataset name=\"/ncml/aggregation/TRMM_3B43\"                     ID=\"/opendap/hyrax/ncml/aggregation/TRMM_3B43/\">             <thredds:dataset name=\"TRMM_3B43_Aggregation.ncml\"                        ID=\"/opendap/hyrax/ncml/aggregation/TRMM_3B43/TRMM_3B43_Aggregation.ncml\">          <thredds:dataSize units=\"bytes\">20722</thredds:dataSize>          <thredds:date type=\"modified\">2014-05-30T14:48:40</thredds:date>          <thredds:access serviceName=\"dap\"                          urlPath=\"/ncml/aggregation/TRMM_3B43/TRMM_3B43_Aggregation.ncml\"/>          <thredds:access serviceName=\"file\"                          urlPath=\"/ncml/aggregation/TRMM_3B43/TRMM_3B43_Aggregation.ncml\"/>       </thredds:dataset>         </thredds:dataset>     </thredds:catalog> ", 
    "identity": {
        "subtype": "service", 
        "is_error": false, 
        "version": "1.0", 
        "protocol": "UNIDATA", 
        "language": "", 
        "service": "THREDDS-Catalog", 
        "has_dataset": true, 
        "has_metadata": true
    }, 
    "digest": "10a2843b11f431b3c70ce435ccac951b", 
    "source_url": "http://disc2.nascom.nasa.gov/opendap/ncml/aggregation/TRMM_3B43/catalog.xml"
}