{
    "content": "<?xml version=\"1.0\" encoding='UTF-8'?>  <reference anchor=\"I-D.murphy-bgp-secr\"> <front> <title>BGP Security Analysis</title>  <author initials=\"S\" surname=\"Murphy\" fullname=\"S. Murphy\">     <organization /> </author>  <date month=\"November\" day=\"30\" year=\"2001\" /> </front>  <seriesInfo name=\"Internet-Draft\" value=\"draft-murphy-bgp-secr-04\" /> </reference> ", 
    "identity": {
        "subtype": "", 
        "is_error": false, 
        "version": "", 
        "protocol": "", 
        "language": "", 
        "service": "", 
        "has_dataset": false, 
        "has_metadata": false
    }, 
    "digest": "1858891066094d080fa946ceb61b4eec", 
    "source_url": "http://xml2rfc.ietf.org/public/rfc/bibxml3/reference.I-D.murphy-bgp-secr.xml"
}