{
    "content": "<?xml version=\"1.0\" encoding=\"UTF-8\"?> <metadata>   <idinfo>     <citation>       <citeinfo>         <pubdate>20141110</pubdate>         <title>Liberia_WADC00275_HR_Refugee_Locations</title>   <origin>temp</origin>                                       <onlink>http://www.humanitarianresponse.info/</onlink>                                  <onlink>http://ebola-data.un.org/Liberia/Liberia_WADC00275_HR_Refugee_Locations/Liberia_WADC00275_HR_Refugee_Locations.zip</onlink>         <geoform>tabular digital data</geoform>         <pubinfo>           <publish>Humanitarian Response</publish>         </pubinfo>       </citeinfo>     </citation>     <descript>       <abstract>Humanitarian Response has published Refugee locations in Liberia on their website in support of the Ebola crisis.</abstract>       <purpose>HR - The HumanitarianResponse.info platform is provided to the humanitarian0.0 community as a means to aid in coordination of operational information and related activities. The technical aspects have been developed and continued to be managed by OCHA as per their responsibilities outlined in the Inter-Agency Standing Committee\\ufffd\\ufffd\\ufffd\\ufffd\\ufffd\\ufffds (IASC) Operational Guidance on Responsibilities Of Cluster/Sector Leads &amp; OCHA In Information Management.</purpose>     </descript>     <timeperd>       <timeinfo>         <sngdate>           <caldate>20141110</caldate>         </sngdate>       </timeinfo>       <current>Unknown</current>     </timeperd>     <status>       <update>Unknown</update>     </status>     <spdom>       <bounding>         <westbc>-11.574783</westbc>         <eastbc>-8.437837</eastbc>         <northbc>8.603811</northbc>         <southbc>4.938499 </southbc>       </bounding>     </spdom>     <keywords>       <theme>         <themekt>Ebola 2014</themekt>         <themekey>Ebola, WWHGD, Human geography, Geospatial, United nations, NGA, Africa, Liberia, HR, Refugee locations, Demographic and Human Population Measures, Land Use and Cover, Medical and Health, Significant Events.</themekey>       </theme>       <theme>         <themekt>ISO 19115 Topic Categories</themekt>         <themekey>health</themekey>         <themekey>planningCadastre</themekey>         <themekey>society</themekey>       </theme>       <place>         <placekt>None</placekt>         <placekey>Liberia</placekey>       </place>     </keywords>     <accconst>None</accconst>     <useconst>Acquired by HR for public use.</useconst>     <ptcontac>       <cntinfo>         <cntorgp>           <cntorg>HR</cntorg>           <cntper>Humanitarian Response</cntper>         </cntorgp>         <cntpos>Data Manager</cntpos>       </cntinfo>     </ptcontac>     <datacred>Humanitarian Response </datacred>     <secinfo>       <secclass>Unclassified</secclass>     </secinfo>     <native>Microsoft Windows 7 Version 6.1 (Build 7601) Service Pack 1; Esri ArcGIS 10.2.0.3348</native>   </idinfo>   <metainfo>     <metd>20150121</metd>     <metc>       <cntinfo>         <cntorgp>           <cntorg>WWHGD</cntorg>           <cntper>World-Wide Human Geography Data</cntper>         </cntorgp>         <cntpos>Metadata Editor</cntpos>   <cntaddr>    <addrtype>test</addrtype>             <state>test</state>         </cntaddr>       </cntinfo>     </metc>     <metstdn>FGDC Content Standard for Digital Geospatial Metadata</metstdn>     <metstdv>FGDC-STD-001-1998</metstdv>     <mettc>local time</mettc>     <metsi>       <metsc>Unclassified</metsc>     </metsi>   </metainfo> </metadata>", 
    "identity": {
        "subtype": "", 
        "is_error": false, 
        "version": "", 
        "protocol": "", 
        "language": "", 
        "service": "", 
        "has_dataset": false, 
        "has_metadata": false
    }, 
    "digest": "1ef1a3d8d50bbf3cd7c331144364fd67", 
    "source_url": "http://catalog.data.gov/harvest/object/6fa6b576-50c6-40d7-9909-152ce18ce419/original"
}