{
    "content": "<xml xmlns:o=\"urn:schemas-microsoft-com:office:office\">  <o:MainFile HRef=\"../Apollo17.htm\"/>  <o:File HRef=\"header.htm\"/>  <o:File HRef=\"filelist.xml\"/> </xml>", 
    "identity": {
        "subtype": "", 
        "is_error": false, 
        "version": "", 
        "protocol": "", 
        "language": "", 
        "service": "", 
        "has_dataset": false, 
        "has_metadata": false
    }, 
    "digest": "3e7cef1341e9ae69ea1248a1b51d52ab", 
    "source_url": "http://eol.jsc.nasa.gov/SearchPhotos/metadata/Apollo17_files/filelist.xml"
}