{
    "content": "<ns0:DIF xmlns:ns0=\"http://gcmd.gsfc.nasa.gov/Aboutus/xml/dif/\"          xmlns:xsi=\"http://www.w3.org/2001/XMLSchema-instance\"          xsi:schemaLocation=\"http://gcmd.gsfc.nasa.gov/Aboutus/xml/dif/ http://gcmd.gsfc.nasa.gov/Aboutus/xml/dif/dif_v9.4.xsd\">    <ns0:Entry_ID>dassh.ac.uk:DIF:2178</ns0:Entry_ID>    <ns0:Entry_Title>Kentish Flats Offshore Wind Farm: Post-Construction Oyster Sampling</ns0:Entry_Title>    <ns0:Parameters>       <ns0:Category/>       <ns0:Topic/>       <ns0:Term>Marine Environmental Data and Information Network</ns0:Term>    </ns0:Parameters>    <ns0:Parameters>       <ns0:Category/>       <ns0:Topic/>       <ns0:Term>Marine Biodiversity</ns0:Term>    </ns0:Parameters>    <ns0:Parameters>       <ns0:Category/>       <ns0:Topic/>       <ns0:Term>Agreement for Lease Area</ns0:Term>    </ns0:Parameters>    <ns0:Parameters>       <ns0:Category/>       <ns0:Topic/>       <ns0:Term>Post-Construction monitoring</ns0:Term>    </ns0:Parameters>    <ns0:Parameters>       <ns0:Category/>       <ns0:Topic/>       <ns0:Term>Shellfish</ns0:Term>    </ns0:Parameters>    <ns0:Parameters>       <ns0:Category/>       <ns0:Topic/>       <ns0:Term>Fisheries and aquaculture</ns0:Term>    </ns0:Parameters>    <ns0:ISO_Topic_Category>biota environment</ns0:ISO_Topic_Category>    <ns0:ISO_Topic_Category>biota environment</ns0:ISO_Topic_Category>    <ns0:Keyword>Marine Environmental Data and Information Network</ns0:Keyword>    <ns0:Keyword>Marine Biodiversity</ns0:Keyword>    <ns0:Keyword>Agreement for Lease Area</ns0:Keyword>    <ns0:Keyword>Post-Construction monitoring</ns0:Keyword>    <ns0:Keyword>Shellfish</ns0:Keyword>    <ns0:Keyword>Fisheries and aquaculture</ns0:Keyword>    <Source_Name xmlns=\"http://gcmd.gsfc.nasa.gov/Aboutus/xml/dif/\">       <Short_Name>NOTE! This GCMD DIF has been produced automatically from ISO19139 MEDIN v2.3 profile.  Not all MEDIN info is reproduced here - this conversion is intended to provide basic information to be reproduced in the NDG/MEDIN discovery service</Short_Name>    </Source_Name>    <ns0:Temporal_Coverage>       <ns0:Start_Date>2005-06-13</ns0:Start_Date>       <ns0:Stop_Date>2005-06-13</ns0:Stop_Date>    </ns0:Temporal_Coverage>    <ns0:Spatial_Coverage>       <ns0:Southernmost_Latitude>51.445122296891</ns0:Southernmost_Latitude>       <ns0:Northernmost_Latitude>51.4747438835695</ns0:Northernmost_Latitude>       <ns0:Westernmost_Longitude>1.05414361147056</ns0:Westernmost_Longitude>       <ns0:Easternmost_Longitude>1.13712757183223</ns0:Easternmost_Longitude>    </ns0:Spatial_Coverage>    <ns0:Data_Center>       <ns0:Data_Center_Name>          <ns0:Short_Name>Kentish Flats Ltd</ns0:Short_Name>       </ns0:Data_Center_Name>       <ns0:Personnel>          <ns0:Role>custodian</ns0:Role>          <ns0:Last_Name>Project manager</ns0:Last_Name>       </ns0:Personnel>    </ns0:Data_Center>    <ns0:Data_Center>       <ns0:Data_Center_Name>          <ns0:Short_Name>Kentish Flats Ltd</ns0:Short_Name>       </ns0:Data_Center_Name>       <ns0:Personnel>          <ns0:Role>originator</ns0:Role>          <ns0:Last_Name>Project manager</ns0:Last_Name>       </ns0:Personnel>    </ns0:Data_Center>    <ns0:Summary>This project concerns the presence of oysters at the site of Kentish Flats Offshore Wind Farm after its construction. A series of field sampling of the local native oysters was undertaken to be able to assess the levels of specific chemicals in the flesh of the oysters. A comparison is made between the pre and post construction results. </ns0:Summary>    <ns0:Related_URL>       <ns0:URL>http://www.marinedataexchange.co.uk/search?q=Kentish Flats Offshore Wind Farm: Post-Construction Oyster Sampling</ns0:URL>    </ns0:Related_URL>    <ns0:Metadata_Name>9.4</ns0:Metadata_Name>    <ns0:Metadata_Version>[CEOS IDN DIF]</ns0:Metadata_Version>    <ns0:DIF_Creation_Date>2005-08-31</ns0:DIF_Creation_Date> </ns0:DIF>", 
    "identity": {
        "subtype": "", 
        "is_error": false, 
        "version": "", 
        "protocol": "", 
        "language": "", 
        "service": "", 
        "has_dataset": false, 
        "has_metadata": false
    }, 
    "digest": "50f731e2db56db6f2ca7f564750a6599", 
    "source_url": "http://portal.oceannet.org/search/full/catalogue/dassh.ac.uk__MEDIN_2.3__782091f5be9c5aeca4d5c1a67de8d97d.xml/DIF_9.4"
}