{
    "content": "<xml xmlns:o=\"urn:schemas-microsoft-com:office:office\">  <o:MainFile HRef=\"../index.htm\"/>  <o:File HRef=\"image328.gif\"/>  <o:File HRef=\"image329.png\"/>  <o:File HRef=\"image332.png\"/>  <o:File HRef=\"image345.png\"/>  <o:File HRef=\"image407.png\"/>  <o:File HRef=\"image422.png\"/>  <o:File HRef=\"image304.png\"/>  <o:File HRef=\"image3041.png\"/>  <o:File HRef=\"image434.png\"/>  <o:File HRef=\"image738.jpg\"/>  <o:File HRef=\"image7381.jpg\"/>  <o:File HRef=\"image1116.png\"/>  <o:File HRef=\"image469.jpg\"/>  <o:File HRef=\"image461.jpg\"/>  <o:File HRef=\"image1598.png\"/>  <o:File HRef=\"Page722.htm\"/>  <o:File HRef=\"image749.png\"/>  <o:File HRef=\"image840.jpg\"/>  <o:File HRef=\"image8401.jpg\"/>  <o:File HRef=\"Page1120.htm\"/>  <o:File HRef=\"image1129.png\"/>  <o:File HRef=\"image1209.jpg\"/>  <o:File HRef=\"image12091.jpg\"/>  <o:File HRef=\"Page843.htm\"/>  <o:File HRef=\"image838.png\"/>  <o:File HRef=\"image818.png\"/>  <o:File HRef=\"image526.png\"/>  <o:File HRef=\"image926.png\"/>  <o:File HRef=\"image939.jpg\"/>  <o:File HRef=\"image9391.jpg\"/>  <o:File HRef=\"Page522.htm\"/>  <o:File HRef=\"image619.png\"/>  <o:File HRef=\"image477.png\"/>  <o:File HRef=\"image539.jpg\"/>  <o:File HRef=\"image5391.jpg\"/>  <o:File HRef=\"Page940.htm\"/>  <o:File HRef=\"image267.png\"/>  <o:File HRef=\"image1073.jpg\"/>  <o:File HRef=\"image10731.jpg\"/>  <o:File HRef=\"Page435.htm\"/>  <o:File HRef=\"image439.png\"/>  <o:File HRef=\"image1099.png\"/>  <o:File HRef=\"image1234.jpg\"/>  <o:File HRef=\"image1236.jpg\"/>  <o:File HRef=\"image1235.png\"/>  <o:File HRef=\"image12351.png\"/>  <o:File HRef=\"image1433.jpg\"/>  <o:File HRef=\"image14331.jpg\"/>  <o:File HRef=\"image817.wmz\"/>  <o:File HRef=\"image8171.png\"/>  <o:File HRef=\"image297.png\"/>  <o:File HRef=\"image2971.png\"/>  <o:File HRef=\"image324.png\"/>  <o:File HRef=\"image934.png\"/>  <o:File HRef=\"image936.jpg\"/>  <o:File HRef=\"image1254.png\"/>  <o:File HRef=\"image1484.jpg\"/>  <o:File HRef=\"image2045.png\"/>  <o:File HRef=\"image20451.png\"/>  <o:File HRef=\"image2047.jpg\"/>  <o:File HRef=\"image2049.png\"/>  <o:File HRef=\"image2053.jpg\"/>  <o:File HRef=\"image2051.gif\"/>  <o:File HRef=\"image20511.png\"/>  <o:File HRef=\"image2055.jpg\"/>  <o:File HRef=\"image2057.jpg\"/>  <o:File HRef=\"image2059.jpg\"/>  <o:File HRef=\"image20591.jpg\"/>  <o:File HRef=\"image2061.jpg\"/>  <o:File HRef=\"image2063.jpg\"/>  <o:File HRef=\"image2065.jpg\"/>  <o:File HRef=\"image2069.png\"/>  <o:File HRef=\"image1229.png\"/>  <o:File HRef=\"filelist.xml\"/> </xml>", 
    "identity": {
        "subtype": "", 
        "is_error": false, 
        "version": "", 
        "protocol": "", 
        "language": "", 
        "service": "", 
        "has_dataset": false, 
        "has_metadata": false
    }, 
    "digest": "72021e81e1cccfb73db7464848cc60fe", 
    "source_url": "http://www.und.nodak.edu/org/urg/index_files/filelist.xml"
}