{
    "content": "<?xml version=\"1.0\"?> <!DOCTYPE XSIL SYSTEM \"http://www.vallis.org/lisa-xml.dtd\"> <?xml-stylesheet type=\"text/xsl\" href=\"lisa-xml.xsl\"?> <XSIL>     <Param Name=\"Author\">MLDC Task Force</Param>     <Param Name=\"GenerationDate\" Type=\"ISO-8601\">2007-08-10T18:04:39CEST</Param>     <Comment>         XML key for challenge1B.1.1c, source seed = 456568, noise seed = 456568, LISAtools SVN revision 491                 lisaXML 1.0 [M. Vallisneri, June 2006]     </Comment>     <XSIL Type=\"LISAData\">         <XSIL Name=\"Standard MLDC PseudoLISA\" Type=\"PseudoLISA\">             <Param Name=\"TimeOffset\" Unit=\"Second\">                 0             </Param>             <Param Name=\"InitialPosition\" Unit=\"Radian\">                 0             </Param>             <Param Name=\"InitialRotation\" Unit=\"Radian\">                 0             </Param>             <Param Name=\"Armlength\" Unit=\"Second\">                 16.6782             </Param>         </XSIL>     </XSIL>     <XSIL Type=\"SourceData\">         <XSIL Name=\"GB-1.1.1c\" Type=\"PlaneWave\">             <Param Name=\"SourceType\">                 GalacticBinary             </Param>             <Param Name=\"EclipticLatitude\" Unit=\"Radian\">                 -0.174698229304             </Param>             <Param Name=\"EclipticLongitude\" Unit=\"Radian\">                 6.06345815939             </Param>             <Param Name=\"Polarization\" Unit=\"Radian\">                 5.59426545687             </Param>             <Param Name=\"Frequency\" Unit=\"Hertz\">                 0.00994347203397             </Param>             <Param Name=\"InitialPhase\" Unit=\"Radian\">                 5.75755296145             </Param>             <Param Name=\"Inclination\" Unit=\"Radian\">                 2.04156232917             </Param>             <Param Name=\"Amplitude\" Unit=\"1\">                 1.38258367651e-23             </Param>         </XSIL>     </XSIL> </XSIL> ", 
    "identity": {
        "subtype": "", 
        "is_error": false, 
        "version": "", 
        "protocol": "", 
        "language": "", 
        "service": "", 
        "has_dataset": false, 
        "has_metadata": false
    }, 
    "digest": "8bfd8d6a7ddd51211b7db5c3feb76e75", 
    "source_url": "http://astrogravs.gsfc.nasa.gov/docs/mldc/round1/round1b/keys/challenge1B.1.1c-key.xml"
}