{
    "content": "<?xml version='1.0' encoding=\"ISO-8859-1\" standalone=\"no\" ?> <!DOCTYPE WMT_MS_Capabilities SYSTEM \"http://schemas.opengis.net/wms/1.0.0/capabilities_1_0_0.dtd\"  [  <!ELEMENT VendorSpecificCapabilities EMPTY>  ]>  <!-- end of DOCTYPE declaration -->  <WMT_MS_Capabilities version=\"1.0.0\">  <!-- MapServer version 6.4.0 OUTPUT=GIF OUTPUT=PNG OUTPUT=JPEG OUTPUT=KML SUPPORTS=PROJ SUPPORTS=GD SUPPORTS=AGG SUPPORTS=FREETYPE SUPPORTS=CAIRO SUPPORTS=ICONV SUPPORTS=WMS_SERVER SUPPORTS=WMS_CLIENT SUPPORTS=WFS_SERVER SUPPORTS=WCS_SERVER SUPPORTS=GEOS INPUT=JPEG INPUT=POSTGIS INPUT=OGR INPUT=GDAL INPUT=SHAPEFILE -->  <Service>   <Name>GetMap</Name>   <Title>National_Geochemical_Survey</Title>   <OnlineResource>http://mrdata.usgs.gov/</OnlineResource>   <Fees>none</Fees>   <AccessConstraints>none</AccessConstraints> </Service>  <Capability>   <Request>     <Map>       <Format><GIF /><PNG /><JPEG /><SVG /></Format>       <DCPType>         <HTTP>           <Get onlineResource=\"http://mrdata.usgs.gov/services/ngs?\" />           <Post onlineResource=\"http://mrdata.usgs.gov/services/ngs?\" />         </HTTP>       </DCPType>     </Map>     <Capabilities>       <Format><WMS_XML /></Format>       <DCPType>         <HTTP>           <Get onlineResource=\"http://mrdata.usgs.gov/services/ngs?\" />           <Post onlineResource=\"http://mrdata.usgs.gov/services/ngs?\" />         </HTTP>       </DCPType>     </Capabilities>     <FeatureInfo>       <Format><MIME /><GML.1 /></Format>       <DCPType>         <HTTP>           <Get onlineResource=\"http://mrdata.usgs.gov/services/ngs?\" />           <Post onlineResource=\"http://mrdata.usgs.gov/services/ngs?\" />         </HTTP>       </DCPType>     </FeatureInfo>   </Request>   <Exception>     <Format><BLANK /><INIMAGE /><WMS_XML /></Format>   </Exception>   <VendorSpecificCapabilities />   <Layer>     <Name>National_Geochemical_Survey</Name>     <Title>National_Geochemical_Survey</Title>     <Abstract>National_Geochemical_Survey</Abstract>     <SRS>EPSG:4267 EPSG:4269 EPSG:4326 EPSG:3857 EPSG:900913 EPSG:102113 EPSG:2964</SRS>     <LatLonBoundingBox minx=\"-165\" miny=\"24\" maxx=\"-66\" maxy=\"73\" />     <BoundingBox SRS=\"EPSG:4267\"                 minx=\"-165\" miny=\"24\" maxx=\"-66\" maxy=\"73\" />     <Layer>       <Name>natgeochem</Name>       <Title>natgeochem</Title>       <Abstract>natgeochem</Abstract>     <Style>        <Name>default</Name>        <Title>default</Title>        <LegendURL width=\"203\" height=\"21\">           <Format>image/png</Format>           <OnlineResource xmlns:xlink=\"http://www.w3.org/1999/xlink\" xlink:type=\"simple\" xlink:href=\"http://mrdata.usgs.gov/services/ngs?version=1.0.0&amp;service=WMS&amp;request=GetLegendGraphic&amp;layer=natgeochem&amp;format=image/png&amp;STYLE=default\"/>        </LegendURL>     </Style>       <Layer queryable=\"1\">         <Name>natgeochem-high</Name>         <Title>natgeochem</Title>         <Abstract>USGS Web Mapping Service:  National Geochemical Survey</Abstract>         <Keywords>geochemistry  unconsolidated deposits         </Keywords>         <SRS>EPSG:4267 EPSG:4269 EPSG:4326 EPSG:3857 EPSG:900913 EPSG:102113 EPSG:2964</SRS>         <LatLonBoundingBox minx=\"-179\" miny=\"6\" maxx=\"159\" maxy=\"72\" />         <BoundingBox SRS=\"EPSG:4267\"                     minx=\"-179\" miny=\"6\" maxx=\"159\" maxy=\"72\" />         <ScaleHint min=\"0\" max=\"2494.51424214819\" />       </Layer>       <Layer queryable=\"1\">         <Name>natgeochem-low</Name>         <Title>natgeochem</Title>         <Abstract>USGS Web Mapping Service:  National Geochemical Survey</Abstract>         <Keywords>geochemistry  unconsolidated deposits         </Keywords>         <SRS>EPSG:4267 EPSG:4269 EPSG:4326 EPSG:3857 EPSG:900913 EPSG:102113 EPSG:2964</SRS>         <LatLonBoundingBox minx=\"-179\" miny=\"6\" maxx=\"159\" maxy=\"72\" />         <BoundingBox SRS=\"EPSG:4267\"                     minx=\"-179\" miny=\"6\" maxx=\"159\" maxy=\"72\" />         <ScaleHint min=\"2494.51424214819\" max=\"0\" />         <!-- WARNING: Only MINSCALEDENOM and no MAXSCALEDENOM specified in the mapfile. A default value of 0 has been returned for the Max ScaleHint but this is probably not what you want. -->       </Layer>     </Layer>   </Layer> </Capability> </WMT_MS_Capabilities> ", 
    "identity": {
        "subtype": "", 
        "is_error": false, 
        "version": "", 
        "protocol": "", 
        "language": "", 
        "service": "", 
        "has_dataset": false, 
        "has_metadata": false
    }, 
    "digest": "c670f4bb89651e3174828fa5e02e50aa", 
    "source_url": "http://mrdata.usgs.gov/services/ngs?request=getcapabilities&service=WMS&version=1.0.0"
}