{
    "content": "<?xml version='1.0' encoding=\"ISO-8859-1\" ?> <schema    targetNamespace=\"http://mapserver.gis.umn.edu/mapserver\"     xmlns:ms=\"http://mapserver.gis.umn.edu/mapserver\"     xmlns:ogc=\"http://www.opengis.net/ogc\"    xmlns:xsd=\"http://www.w3.org/2001/XMLSchema\"    xmlns=\"http://www.w3.org/2001/XMLSchema\"    xmlns:gml=\"http://www.opengis.net/gml\"    elementFormDefault=\"qualified\" version=\"0.1\" >    <import namespace=\"http://www.opengis.net/gml\"           schemaLocation=\"http://schemas.opengis.net/gml/3.1.1/base/gml.xsd\" />    <element name=\"ardf\"             type=\"ms:ardfType\"             substitutionGroup=\"gml:_Feature\" />    <complexType name=\"ardfType\">     <complexContent>       <extension base=\"gml:AbstractFeatureType\">         <sequence>           <element name=\"geometry\" type=\"gml:PointPropertyType\" minOccurs=\"0\" maxOccurs=\"1\"/>           <element name=\"site_type\" type=\"string\"/>           <element name=\"site\" type=\"string\"/>           <element name=\"ardf_num\" type=\"string\"/>           <element name=\"url\" type=\"string\"/>         </sequence>       </extension>     </complexContent>   </complexType>  </schema> ", 
    "identity": {
        "subtype": "", 
        "is_error": false, 
        "version": "", 
        "protocol": "", 
        "language": "", 
        "service": "", 
        "has_dataset": false, 
        "has_metadata": false
    }, 
    "digest": "f943e0c403df7e414d2324ba89d4b116", 
    "source_url": "http://mrdata.usgs.gov/wfs/ardf?request=describefeaturetype&service=WFS&version=1.1.0&typename=ardf"
}